r4n/__init__.py
r4n/main.py
remote4neovim-0.0.1.dist-info/LICENSE
remote4neovim-0.0.1.dist-info/METADATA
remote4neovim-0.0.1.dist-info/WHEEL
remote4neovim-0.0.1.dist-info/entry_points.txt
remote4neovim-0.0.1.dist-info/top_level.txt
remote4neovim-0.0.1.dist-info/RECORD
